{
    "_links": {
        "self": {
            "href": "https:\/\/8080-emilyvargas-proyectofin-nint8ac9u9z.ws-us100.gitpod.io\/sites\/default\/files\/2023-06\/generateImage_wF2uPN.gif"
        },
        "type": {
            "href": "https:\/\/8080-emilyvargas-proyectofin-nint8ac9u9z.ws-us100.gitpod.io\/rest\/type\/file\/file"
        }
    },
    "fid": [
        {
            "value": 20
        }
    ],
    "uuid": [
        {
            "value": "86804831-8146-4dd2-8f40-a43ddd5a4ed8"
        }
    ],
    "langcode": [
        {
            "value": "en"
        }
    ],
    "filename": [
        {
            "value": "generateImage_wF2uPN.gif"
        }
    ],
    "uri": [
        {
            "value": "public:\/\/2023-06\/generateImage_wF2uPN.gif",
            "url": "\/sites\/default\/files\/2023-06\/generateImage_wF2uPN.gif"
        }
    ],
    "filemime": [
        {
            "value": "image\/gif"
        }
    ],
    "filesize": [
        {
            "value": 1183
        }
    ],
    "status": [
        {
            "value": true
        }
    ],
    "created": [
        {
            "value": "2023-06-06T04:00:31+00:00",
            "format": "Y-m-d\\TH:i:sP"
        }
    ],
    "changed": [
        {
            "value": "2023-06-06T04:00:31+00:00",
            "format": "Y-m-d\\TH:i:sP"
        }
    ]
}